pyimgcaptcha/__init__.py
pyimgcaptcha/module.py
pyimgcaptcha-0.1.2.dist-info/licenses/LICENSE
pyimgcaptcha-0.1.2.dist-info/METADATA
pyimgcaptcha-0.1.2.dist-info/WHEEL
pyimgcaptcha-0.1.2.dist-info/top_level.txt
pyimgcaptcha-0.1.2.dist-info/RECORD
