Metadata-Version: 2.4
Name: pyimgcaptcha
Version: 0.1.2
Summary: Library for generating CAPTCHA images
Author: redderi
Author-email: redderi <vrudko22@gmail.com>
License: MIT
Classifier: Programming Language :: Python :: 3
Classifier: License :: OSI Approved :: MIT License
Classifier: Operating System :: OS Independent
Requires-Python: >=3.6
License-File: LICENSE
Requires-Dist: Pillow>=8.0.0
Dynamic: author
Dynamic: license-file
Dynamic: requires-python
